{
  "menu": [
    {
        "key": "2020-04-24-11",
        "start": "2020-04-24 11:00:00",
        "banner": {
          "type": "notice",
          "contents": [
            "MIP Cache 服务下线通知。>> 详情"
          ]
        }
    },
    {
      "key": "2019-09-23-19",
      "start": "2019-09-23 19:00:00",
      "banner": {
        "type": "notice",
        "contents": [
          "MIP站长组件审核平台维护通知。>> 详情"
        ]
      }
    },
    {
      "key": "2019-04-28-14",
      "start": "2019-04-28 14:00:00",
      "end": "2019-09-01 00:00:00",
      "banner": {
        "type": "notice",
        "contents": [
          "MIP 2.0 站长组件迁移开始启动，请各位 MIP 组件开发者开始准备站长组件的迁移。>> 详情"
        ]
      }
    }
  ]
}
